{"cameraMode":{"drawMode":0,"name":"Shaded","section":"Shading Mode"},"sceneLighting":true,"audioPlay":false,"sceneViewState":{"m_AlwaysRefresh":false,"showFog":true,"showSkybox":true,"showFlares":true,"showImageEffects":true,"showParticleSystems":true,"showVisualEffectGraphs":true,"m_FxEnabled":true},"in2DMode":false,"pivot":{"x":7.755064010620117,"y":-2.931652069091797,"z":-18.622949600219728},"rotation":{"x":0.48545679450035097,"y":0.2746533155441284,"z":-0.16381165385246278,"w":0.8137166500091553},"size":4.247499465942383,"orthographic":false}